rtl/memory.sv
`timescale 1ns/1ps


module memory #(
    parameter int WORDS = 128,
    parameter string mem_init = ""
) (
    input logic        clk,
    input logic [31:0] address,
    input logic [31:0] write_data,
    input logic        write_enable,
    input logic        rst_n,
    input logic [3:0]  byte_enable,

    output logic [31:0] read_data
);

    logic [31:0] mem [0:WORDS-1];

    // MEMORY INITIALIZATION

    initial begin
        if (mem_init != "") begin
            $display("Loading memory from %s", mem_init);
            $readmemh(mem_init, mem);
        end
    end

    // WRITE LOGIC

    always_ff @(posedge clk) begin
        if (!rst_n) begin

        end

        else if (write_enable) begin
            if (address[1:0] != 2'b00) begin
                $fatal(1, "Misaligned write at address %h", address);
            end

            else begin

                if (byte_enable[0])
                    mem[address[31:2]][7:0] <= write_data[7:0];

                if (byte_enable[1])
                    mem[address[31:2]][15:8] <= write_data[15:8];

                if (byte_enable[2])
                    mem[address[31:2]][23:16] <= write_data[23:16];

                if (byte_enable[3])
                    mem[address[31:2]][31:24] <= write_data[31:24];

            end
        end
    end

    // READ LOGIC

    always_comb begin
        read_data = 32'h00000000;

        if (address[1:0] != 2'b00) begin
          //  $fatal(1, "Misaligned read at address %h", address); //add later
        end

        else begin
            read_data = mem[address[31:2]];
        end
    end

endmodule

rtl/regfile.sv
`timescale 1ns/1ps

module regfile (
    input  logic        clk,
    input  logic        rst,
    input  logic [4:0]  rs1,
    input  logic [4:0]  rs2,
    input  logic [4:0]  rd,
    input  logic [31:0] write_data,
    input  logic        write_enable,
    output logic [31:0] data1,
    output logic [31:0] data2
);

    logic [31:0] registers [0:31];

    // Reads: combinational, x0 hardwired to zero
    always_comb begin
        data1 = (rs1 == 5'd0) ? 32'd0 : registers[rs1];
        data2 = (rs2 == 5'd0) ? 32'd0 : registers[rs2];
    end

    // Writes: NEGEDGE = the half-cycle write trick.
    // A write lands mid-cycle; an ID read in the second half sees fresh data.
    always_ff @(negedge clk) begin
        if (rst) begin
            for (int i = 0; i < 32; i++) registers[i] <= 32'd0;
        end else if (write_enable && rd != 5'd0) begin
            registers[rd] <= write_data;
        end
    end

endmodule

rtl/reader.sv
`timescale 1ns/1ps

import cpu_package::*;

module reader (
    input  logic [31:0] mem_data,
    input  logic [31:0] alu_result,
    input  logic [2:0]  funct3,

    output logic [31:0] read_data
);

logic [1:0] offset;
logic       sign_extend;

assign offset = alu_result[1:0];
assign sign_extend = ~funct3[2];

always_comb begin
    read_data = 32'b0;

    case (funct3)

        3'b000, 3'b100: begin // LB / LBU
            case (offset)
                2'b00: read_data = {{24{sign_extend & mem_data[7]}},  mem_data[7:0]};
                2'b01: read_data = {{24{sign_extend & mem_data[15]}}, mem_data[15:8]};
                2'b10: read_data = {{24{sign_extend & mem_data[23]}}, mem_data[23:16]};
                2'b11: read_data = {{24{sign_extend & mem_data[31]}}, mem_data[31:24]};
            endcase
        end

        3'b001, 3'b101: begin // LH / LHU
            case (offset)
                2'b00: read_data = {{16{sign_extend & mem_data[15]}}, mem_data[15:0]};
                2'b10: read_data = {{16{sign_extend & mem_data[31]}}, mem_data[31:16]};
                default: read_data = 32'b0;
            endcase
        end

        3'b010: begin // LW
            if (offset == 2'b00)
                read_data = mem_data;
        end

        default: begin
            read_data = 32'b0;
        end

    endcase
end

endmodule

rtl/load_store_decoder.sv
`timescale 1ns/1ps

import cpu_package::*;

module load_store_decoder (
    input  logic [31:0] alu_result,
    input  logic [2:0]  funct3,
    input  logic [31:0] reg_read,

    output logic [31:0] data,
    output logic [3:0]  byte_enable
);

logic [1:0] offset;

assign offset = alu_result[1:0];

always_comb begin
    data = 32'b0;
    byte_enable = 4'b0000;

    case (funct3)

        3'b000: begin // SB
            case (offset)
                2'b00: begin
                    data = reg_read & 32'h000000FF;
                    byte_enable = 4'b0001;
                end
                2'b01: begin
                    data = (reg_read & 32'h000000FF) << 8;
                    byte_enable = 4'b0010;
                end
                2'b10: begin
                    data = (reg_read & 32'h000000FF) << 16;
                    byte_enable = 4'b0100;
                end
                2'b11: begin
                    data = (reg_read & 32'h000000FF) << 24;
                    byte_enable = 4'b1000;
                end
            endcase
        end

        3'b001: begin // SH
            case (offset)
                2'b00: begin
                    data = reg_read & 32'h0000FFFF;
                    byte_enable = 4'b0011;
                end
                2'b10: begin
                    data = (reg_read & 32'h0000FFFF) << 16;
                    byte_enable = 4'b1100;
                end
            endcase
        end

        3'b010: begin // SW
            if (offset == 2'b00) begin
                data = reg_read;
                byte_enable = 4'b1111;
            end
        end

        default: begin
            data = 32'b0;
            byte_enable = 4'b0000;
        end

    endcase
end

endmodule

rtl/alu.sv
`timescale 1ns/1ps

import cpu_package::*;

module alu (
    input  logic [3:0]  alu_control,
    input  logic [31:0] src1,
    input  logic [31:0] src2,

    output logic [31:0] alu_result,
    output logic        zero,
    output logic        last_bit
);

    logic [4:0] shamt;

    assign shamt = src2[4:0];

    always_comb begin

        case (alu_control)

            ALU_ADD:
                alu_result = src1 + src2;

            ALU_SUB:
                alu_result = src1 - src2;

            ALU_AND:
                alu_result = src1 & src2;

            ALU_OR:
                alu_result = src1 | src2;

            ALU_XOR:
                alu_result = src1 ^ src2;

            ALU_SLL:
                alu_result = src1 << shamt;

            ALU_SRL:
                alu_result = src1 >> shamt;

            ALU_SRA:
                alu_result = $signed(src1) >>> shamt;

            ALU_SLT:
                alu_result = {31'b0, ($signed(src1) < $signed(src2))};

            ALU_SLTU:
                alu_result = {31'b0, (src1 < src2)};

            default:
                alu_result = 32'b0;

        endcase

    end

    assign zero = (alu_result == 32'b0);

    assign last_bit = alu_result[0];

endmodule

rtl/signext.sv
`timescale 1ns/1ps

module signext (
    input  logic [24:0] raw_src,
    input  logic [2:0]  imm_source,

    output logic [31:0] immediate
);

    always_comb begin

        case (imm_source)

            // I-type
            3'b000:
                immediate = {{20{raw_src[24]}},
                             raw_src[24:13]};

            // S-type
            3'b001:
                immediate = {{20{raw_src[24]}},
                             raw_src[24:18],
                             raw_src[4:0]};

            // B-type
            3'b010:
                immediate = {{19{raw_src[24]}},
                             raw_src[24],
                             raw_src[0],
                             raw_src[23:18],
                             raw_src[4:1],
                             1'b0};

            // J-type
            3'b011:
                immediate = {{11{raw_src[24]}},
                             raw_src[24],
                             raw_src[12:5],
                             raw_src[13],
                             raw_src[23:14],
                             1'b0};

            // U-type
            3'b100:
                immediate = {raw_src[24:5],
                             12'b0};

            default:
                immediate = 32'b0;

        endcase

    end

endmodule

rtl/control.sv
`timescale 1ns/1ps
import cpu_package::*;

module control (
    input  logic [6:0] opcode,
    input  logic [2:0] funct3,
    input  logic [6:0] funct7,

    output logic [3:0] alu_control,
    output logic [2:0] imm_source,
    output logic       alu_src,
    output logic       reg_write,
    output logic       mem_write,
    output logic [1:0] result_src,
    output logic       branch,
    output logic       jump,
    output logic [2:0] branch_type
);


always_comb begin
    alu_control = ALU_ADD;
    imm_source  = IMM_I;
    alu_src     = ALU_SRC_REG;
    reg_write   = 1'b0;
    mem_write   = 1'b0;
    result_src  = WRITEBACK_ALU;
    branch      = 1'b0;
    jump        = 1'b0;
    branch_type = BR_BEQ;

    case (opcode)

        OPCODE_RTYPE: begin
            reg_write = 1'b1;

            case (funct3)
                3'b000: alu_control = funct7[5] ? ALU_SUB : ALU_ADD;
                3'b001: alu_control = ALU_SLL;
                3'b010: alu_control = ALU_SLT;
                3'b011: alu_control = ALU_SLTU;
                3'b100: alu_control = ALU_XOR;
                3'b101: alu_control = funct7[5] ? ALU_SRA : ALU_SRL;
                3'b110: alu_control = ALU_OR;
                3'b111: alu_control = ALU_AND;
                default: alu_control = ALU_ADD;
            endcase
        end

        OPCODE_ITYPE: begin
            reg_write  = 1'b1;
            alu_src    = ALU_SRC_IMM;
            imm_source = IMM_I;

            case (funct3)
                3'b000: alu_control = ALU_ADD;
                3'b001: alu_control = ALU_SLL;
                3'b010: alu_control = ALU_SLT;
                3'b011: alu_control = ALU_SLTU;
                3'b100: alu_control = ALU_XOR;
                3'b101: alu_control = funct7[5] ? ALU_SRA : ALU_SRL;
                3'b110: alu_control = ALU_OR;
                3'b111: alu_control = ALU_AND;
                default: alu_control = ALU_ADD;
            endcase
        end

        OPCODE_LOAD: begin
            alu_control = ALU_ADD;
            alu_src = ALU_SRC_IMM;
            imm_source = IMM_I;
            reg_write = 1'b1;
            result_src = WRITEBACK_MEMORY;
        end

        OPCODE_STORE: begin
            alu_control = ALU_ADD;
            alu_src = ALU_SRC_IMM;
            imm_source = IMM_S;
            mem_write = 1'b1;
        end

        OPCODE_BRANCH: begin
            alu_control = ALU_SUB;
            imm_source = IMM_B;
            branch = 1'b1;

            case (funct3)
                3'b000: branch_type = BR_BEQ;
                3'b001: branch_type = BR_BNE;
                3'b100: branch_type = BR_BLT;
                3'b101: branch_type = BR_BGE;
                3'b110: branch_type = BR_BLTU;
                3'b111: branch_type = BR_BGEU;
                default: branch_type = BR_BEQ;
            endcase
        end

        OPCODE_JAL: begin
            imm_source = IMM_J;
            reg_write = 1'b1;
            result_src = WRITEBACK_PC4;
            jump = 1'b1;
        end

        OPCODE_JALR: begin
            alu_control = ALU_ADD;
            alu_src = ALU_SRC_IMM;
            imm_source = IMM_I;
            reg_write = 1'b1;
            result_src = WRITEBACK_PC4;
            jump = 1'b1;
        end

        OPCODE_LUI: begin
            imm_source = IMM_U;
            reg_write = 1'b1;
            result_src = WRITEBACK_IMM;
        end

        OPCODE_AUIPC: begin
            alu_control = ALU_ADD;
            alu_src = ALU_SRC_IMM;
            imm_source = IMM_U;
            reg_write = 1'b1;
        end

        default: begin
            alu_control = ALU_ADD;
        end

    endcase
end

endmodule

rtl/program_counter.sv
`timescale 1ns/1ps

module program_counter (
    input  logic        clk,
    input  logic        reset,
    input  logic [31:0] next_pc,
    output logic [31:0] pc
);

    always_ff @(posedge clk) begin
        if (reset)
            pc <= 32'd0;
        else
            pc <= next_pc;
    end

endmodule

rtl/cpu.sv
`timescale 1ns/1ps

import cpu_package::*;

module cpu (
    input  logic        rst_n,
    input  logic        clk,

    output logic [31:0] instr_address,
    input  logic [31:0] instr_rdata,

    input  logic [31:0] data_rdata,
    output logic [31:0] data_address,
    output logic [31:0] data_writedata,
    output logic        data_writeenable,
    output logic [3:0]  data_byteenable
);

    logic [31:0] pc;
    logic [31:0] pc_next;
    logic [31:0] pc_plus4;
    logic [31:0] pc_target;

    logic [6:0] opcode;
    logic [6:0] funct7;
    logic [4:0] rs1;
    logic [4:0] rs2;
    logic [4:0] rd;
    logic [2:0] funct3;

    logic [31:0] read_reg1;
    logic [31:0] read_reg2;
    logic [31:0] writeback_data;
    logic [31:0] immediate;

    logic [31:0] alu_src1;
    logic [31:0] alu_src2;
    logic [31:0] alu_result;

    logic [31:0] store_data;
    logic [31:0] load_data;

    logic [3:0] alu_control;
    logic [2:0] imm_source;
    logic [2:0] branch_type;
    logic [1:0] result_src;

    logic alu_src;
    logic reg_write;
    logic mem_write;
    logic branch;
    logic jump;

    logic alu_zero;
    logic alu_last_bit;
    logic branch_taken;

    assign opcode = instr_rdata[6:0];
    assign rd     = instr_rdata[11:7];
    assign funct3 = instr_rdata[14:12];
    assign rs1    = instr_rdata[19:15];
    assign rs2    = instr_rdata[24:20];
    assign funct7 = instr_rdata[31:25];

    assign instr_address = pc;
    assign pc_plus4 = pc + 32'd4;

    always_comb begin
        case (branch_type)
            BR_BEQ:  branch_taken = (read_reg1 == read_reg2);
            BR_BNE:  branch_taken = (read_reg1 != read_reg2);
            BR_BLT:  branch_taken = ($signed(read_reg1) <  $signed(read_reg2));
            BR_BGE:  branch_taken = ($signed(read_reg1) >= $signed(read_reg2));
            BR_BLTU: branch_taken = (read_reg1 <  read_reg2);
            BR_BGEU: branch_taken = (read_reg1 >= read_reg2);
            default: branch_taken = 1'b0;
        endcase
    end

    always_comb begin
        if (jump && opcode == OPCODE_JALR)
            pc_target = (read_reg1 + immediate) & 32'hffff_fffe;
        else
            pc_target = pc + immediate;

        if (jump || (branch && branch_taken))
            pc_next = pc_target;
        else
            pc_next = pc_plus4;
    end

    program_counter u_pc (
        .clk     (clk),
        .reset   (~rst_n),
        .next_pc (pc_next),
        .pc      (pc)
    );

    control u_control (
        .opcode      (opcode),
        .funct3      (funct3),
        .funct7      (funct7),
        .alu_control (alu_control),
        .imm_source  (imm_source),
        .alu_src     (alu_src),
        .reg_write   (reg_write),
        .mem_write   (mem_write),
        .result_src  (result_src),
        .branch      (branch),
        .jump        (jump),
        .branch_type (branch_type)
    );

    signext u_signext (
        .raw_src    (instr_rdata[31:7]),
        .imm_source (imm_source),
        .immediate  (immediate)
    );

    assign alu_src1 = (opcode == OPCODE_AUIPC) ? pc : read_reg1;
    assign alu_src2 = alu_src ? immediate : read_reg2;

    alu u_alu (
        .alu_control (alu_control),
        .src1        (alu_src1),
        .src2        (alu_src2),
        .alu_result  (alu_result),
        .zero        (alu_zero),
        .last_bit    (alu_last_bit)
    );

    load_store_decoder u_store_decoder (
        .alu_result  (alu_result),
        .funct3      (funct3),
        .reg_read    (read_reg2),
        .data        (store_data),
        .byte_enable (data_byteenable)
    );

    assign data_address     = {alu_result[31:2], 2'b00};
    assign data_writedata   = store_data;
    assign data_writeenable = mem_write;

    reader u_reader (
        .mem_data   (data_rdata),
        .alu_result (alu_result),
        .funct3     (funct3),
        .read_data  (load_data)
    );

    always_comb begin
        case (result_src)
            WRITEBACK_ALU:    writeback_data = alu_result;
            WRITEBACK_MEMORY: writeback_data = load_data;
            WRITEBACK_PC4:    writeback_data = pc_plus4;
            WRITEBACK_IMM:    writeback_data = immediate;
            default:          writeback_data = 32'd0;
        endcase
    end

    regfile u_regfile (
        .clk          (clk),
        .rst          (~rst_n),
        .rs1          (rs1),
        .rs2          (rs2),
        .rd           (rd),
        .write_data   (writeback_data),
        .write_enable (reg_write),
        .data1        (read_reg1),
        .data2        (read_reg2)
    );

endmodule

tb/cpu/cpu_harness.sv
`timescale 1ns/1ps

module cpu_harness (
    input logic clk,
    input logic rst_n
);

    logic [31:0] instr_address;
    logic [31:0] instr_rdata;

    logic [31:0] data_address;
    logic [31:0] data_writedata;
    logic [31:0] data_rdata;
    logic        data_writeenable;
    logic [3:0]  data_byteenable;

    cpu u_cpu (
        .clk              (clk),
        .rst_n            (rst_n),
        .instr_address    (instr_address),
        .instr_rdata      (instr_rdata),
        .data_address     (data_address),
        .data_writedata   (data_writedata),
        .data_writeenable (data_writeenable),
        .data_byteenable  (data_byteenable),
        .data_rdata       (data_rdata)
    );

    memory #(
        .WORDS(64),
        .mem_init("test_imemory.hex")
    ) u_imem (
        .clk          (clk),
        .rst_n        (rst_n),
        .address      (instr_address),
        .write_data   (32'd0),
        .write_enable (1'b0),
        .byte_enable  (4'b0000),
        .read_data    (instr_rdata)
    );

    memory #(
        .WORDS(64),
        .mem_init("test_dmemory.hex")
    ) u_dmem (
        .clk          (clk),
        .rst_n        (rst_n),
        .address      (data_address),
        .write_data   (data_writedata),
        .write_enable (data_writeenable),
        .byte_enable  (data_byteenable),
        .read_data    (data_rdata)
    );

    initial begin
        $dumpfile("../../sim/cpu/cpu_wave.vcd");
        $dumpvars(0, cpu_harness);
    end

endmodule

sim/cpu/cpu_wave.vcd
$date
	Wed Sep 02 02:35:37 2026
$end
$version
	Icarus Verilog
$end
$timescale
	1ps
$end
$scope module cpu_harness $end
$var wire 1 ! clk $end
$var wire 1 " rst_n $end
$var wire 32 # instr_rdata [31:0] $end
$var wire 32 $ instr_address [31:0] $end
$var wire 1 % data_writeenable $end
$var wire 32 & data_writedata [31:0] $end
$var wire 32 ' data_rdata [31:0] $end
$var wire 4 ( data_byteenable [3:0] $end
$var wire 32 ) data_address [31:0] $end
$scope module u_cpu $end
$var wire 1 ! clk $end
$var wire 32 * data_writedata [31:0] $end
$var wire 1 % data_writeenable $end
$var wire 32 + instr_address [31:0] $end
$var wire 1 " rst_n $end
$var wire 32 , store_data [31:0] $end
$var wire 5 - rs2 [4:0] $end
$var wire 5 . rs1 [4:0] $end
$var wire 2 / result_src [1:0] $end
$var wire 1 0 reg_write $end
$var wire 32 1 read_reg2 [31:0] $end
$var wire 32 2 read_reg1 [31:0] $end
$var wire 5 3 rd [4:0] $end
$var wire 32 4 pc_plus4 [31:0] $end
$var wire 32 5 pc [31:0] $end
$var wire 7 6 opcode [6:0] $end
$var wire 1 7 mem_write $end
$var wire 32 8 load_data [31:0] $end
$var wire 1 9 jump $end
$var wire 32 : instr_rdata [31:0] $end
$var wire 32 ; immediate [31:0] $end
$var wire 3 < imm_source [2:0] $end
$var wire 7 = funct7 [6:0] $end
$var wire 3 > funct3 [2:0] $end
$var wire 32 ? data_rdata [31:0] $end
$var wire 4 @ data_byteenable [3:0] $end
$var wire 32 A data_address [31:0] $end
$var wire 3 B branch_type [2:0] $end
$var wire 1 C branch $end
$var wire 1 D alu_zero $end
$var wire 32 E alu_src2 [31:0] $end
$var wire 32 F alu_src1 [31:0] $end
$var wire 1 G alu_src $end
$var wire 32 H alu_result [31:0] $end
$var wire 1 I alu_last_bit $end
$var wire 4 J alu_control [3:0] $end
$var reg 1 K branch_taken $end
$var reg 32 L pc_next [31:0] $end
$var reg 32 M pc_target [31:0] $end
$var reg 32 N writeback_data [31:0] $end
$scope module u_alu $end
$var wire 32 O src1 [31:0] $end
$var wire 32 P src2 [31:0] $end
$var wire 1 D zero $end
$var wire 5 Q shamt [4:0] $end
$var wire 1 I last_bit $end
$var wire 4 R alu_control [3:0] $end
$var reg 32 S alu_result [31:0] $end
$upscope $end
$scope module u_control $end
$var wire 3 T funct3 [2:0] $end
$var wire 7 U funct7 [6:0] $end
$var wire 7 V opcode [6:0] $end
$var reg 4 W alu_control [3:0] $end
$var reg 1 G alu_src $end
$var reg 1 C branch $end
$var reg 3 X branch_type [2:0] $end
$var reg 3 Y imm_source [2:0] $end
$var reg 1 9 jump $end
$var reg 1 7 mem_write $end
$var reg 1 0 reg_write $end
$var reg 2 Z result_src [1:0] $end
$upscope $end
$scope module u_pc $end
$var wire 1 ! clk $end
$var wire 32 [ next_pc [31:0] $end
$var wire 1 \ reset $end
$var reg 32 ] pc [31:0] $end
$upscope $end
$scope module u_reader $end
$var wire 32 ^ alu_result [31:0] $end
$var wire 3 _ funct3 [2:0] $end
$var wire 1 ` sign_extend $end
$var wire 2 a offset [1:0] $end
$var wire 32 b mem_data [31:0] $end
$var reg 32 c read_data [31:0] $end
$upscope $end
$scope module u_regfile $end
$var wire 1 ! clk $end
$var wire 5 d rd [4:0] $end
$var wire 5 e rs1 [4:0] $end
$var wire 5 f rs2 [4:0] $end
$var wire 1 g rst $end
$var wire 32 h write_data [31:0] $end
$var wire 1 0 write_enable $end
$var reg 32 i data1 [31:0] $end
$var reg 32 j data2 [31:0] $end
$var integer 32 k i [31:0] $end
$upscope $end
$scope module u_signext $end
$var wire 3 l imm_source [2:0] $end
$var wire 25 m raw_src [24:0] $end
$var reg 32 n immediate [31:0] $end
$upscope $end
$scope module u_store_decoder $end
$var wire 32 o alu_result [31:0] $end
$var wire 3 p funct3 [2:0] $end
$var wire 32 q reg_read [31:0] $end
$var wire 2 r offset [1:0] $end
$var reg 4 s byte_enable [3:0] $end
$var reg 32 t data [31:0] $end
$upscope $end
$upscope $end
$scope module u_dmem $end
$var wire 32 u address [31:0] $end
$var wire 4 v byte_enable [3:0] $end
$var wire 1 ! clk $end
$var wire 1 " rst_n $end
$var wire 32 w write_data [31:0] $end
$var wire 1 % write_enable $end
$var parameter 32 x WORDS $end
$var parameter 128 y mem_init $end
$var reg 32 z read_data [31:0] $end
$upscope $end
$scope module u_imem $end
$var wire 32 { address [31:0] $end
$var wire 4 | byte_enable [3:0] $end
$var wire 1 ! clk $end
$var wire 1 " rst_n $end
$var wire 32 } write_data [31:0] $end
$var wire 1 ~ write_enable $end
$var parameter 32 !" WORDS $end
$var parameter 128 "" mem_init $end
$var reg 32 #" read_data [31:0] $end
$upscope $end
$upscope $end
$enddefinitions $end
$comment Show the parameter values. $end
$dumpall
b1110100011001010111001101110100010111110110100101101101011001010110110101101111011100100111100100101110011010000110010101111000 ""
b1000000 !"
b1110100011001010111001101110100010111110110010001101101011001010110110101101111011100100111100100101110011010000110010101111000 y
b1000000 x
$end
#0
$dumpvars
b100000000000000000010010011 #"
0~
b0 }
b0 |
b0 {
b0 z
b0 w
b1 v
b1000000 u
b0 t
b1 s
b0 r
b0 q
b0 p
b1000000 o
b1000000 n
b10000000000000000001 m
b0 l
b100000 k
b0 j
b0 i
b1000000 h
1g
b0 f
b0 e
b1 d
b0 c
b0 b
b0 a
1`
b0 _
b1000000 ^
b0 ]
1\
b100 [
b0 Z
b0 Y
b0 X
b0 W
b10011 V
b10 U
b0 T
b1000000 S
b0 R
b0 Q
b1000000 P
b0 O
b1000000 N
b1000000 M
b100 L
1K
b0 J
0I
b1000000 H
1G
b0 F
b1000000 E
0D
0C
b0 B
b1000000 A
b1 @
b0 ?
b0 >
b10 =
b0 <
b1000000 ;
b100000000000000000010010011 :
09
b0 8
07
b10011 6
b0 5
b100 4
b1 3
b0 2
b0 1
10
b0 /
b0 .
b0 -
b0 ,
b0 +
b0 *
b1000000 )
b1 (
b0 '
b0 &
0%
b0 $
b100000000000000000010010011 #
0"
1!
$end
#5000
0!
#10000
0\
0g
1"
b100000 k
1!
#15000
0!
#20000
bx 8
bx c
bx '
bx ?
bx b
bx z
b11111111111111111111111110000000 )
b11111111111111111111111110000000 A
b11111111111111111111111110000000 u
b11111111111111111111111110000000 N
b11111111111111111111111110000000 h
b11111111111111111111111110000000 H
b11111111111111111111111110000000 S
b11111111111111111111111110000000 ^
b11111111111111111111111110000000 o
b11111111111111111111111110000000 E
b11111111111111111111111110000000 P
b11111111111111111111111110000000 ;
b11111111111111111111111110000000 n
10
1G
b1111100000000000000000010 m
b1111100 =
b1111100 U
b10 3
b10 d
b1000 L
b1000 [
b11111111111111111111111110000100 M
b11111000000000000000000100010011 #
b11111000000000000000000100010011 :
b11111000000000000000000100010011 #"
b1000 4
b100 $
b100 +
b100 {
b100 5
b100 ]
1!
#25000
0!
#30000
b0 8
b0 c
b0 '
b0 ?
b0 b
b0 z
1I
b1 a
b1 r
b1000000 )
b1000000 A
b1000000 u
b1000001 N
b1000001 h
b1000001 H
b1000001 S
b1000001 ^
b1000001 o
b1 Q
b1000000000000000 &
b1000000000000000 *
b1000000000000000 w
b1000000000000000 ,
b1000000000000000 t
b10 (
b10 @
b10 s
b10 v
b1000000 F
b1000000 O
0K
b1 E
b1 P
b11111111111111111111111110000000 1
b11111111111111111111111110000000 j
b11111111111111111111111110000000 q
b1000000 2
b1000000 i
b1 ;
b1 n
1%
17
b1 <
b1 Y
b1 l
00
1G
b10 -
b10 f
b1 .
b1 e
b100000100000001 m
b0 =
b0 U
b1 3
b1 d
b100011 6
b100011 V
b1100 L
b1100 [
b1001 M
b1000001000000010100011 #
b1000001000000010100011 :
b1000001000000010100011 #"
b1100 4
b1000 $
b1000 +
b1000 {
b1000 5
b1000 ]
1!
#35000
0!
#40000
0`
1K
b10000000 N
b10000000 h
b0 (
b0 @
b0 s
b0 v
b0 &
b0 *
b0 w
b0 ,
b0 t
b1000000 1
b1000000 j
b1000000 q
b1 /
b1 Z
10
0%
07
1G
b0 <
b0 Y
b0 l
b100 >
b100 T
b100 _
b100 p
b10000110000011 m
b1 -
b1 f
b11 3
b11 d
b11 6
b11 V
b10000000 8
b10000000 c
b10000 L
b10000 [
b1101 M
b100001100000110000011 #
b100001100000110000011 :
b100001100000110000011 #"
b1000000000000000 '
b1000000000000000 ?
b1000000000000000 b
b1000000000000000 z
b10000 4
b1100 $
b1100 +
b1100 {
b1100 5
b1100 ]
1!
#45000
0!
#50000
bx '
bx ?
bx b
bx z
b11 a
b11 r
b100100000 )
b100100000 A
b100100000 u
b100100011 H
b100100011 S
b100100011 ^
b100100011 o
b11 Q
b0 F
b0 O
0K
1`
b100100011 N
b100100011 h
b100100011 E
b100100011 P
b100100011 ;
b100100011 n
b10000000 1
b10000000 j
b10000000 q
b0 2
b0 i
bx 8
bx c
b1000 (
b1000 @
b1000 s
b1000 v
b10000000000000000000000000000000 &
b10000000000000000000000000000000 *
b10000000000000000000000000000000 w
b10000000000000000000000000000000 ,
b10000000000000000000000000000000 t
b0 /
b0 Z
10
1G
b1001 =
b1001 U
b1001000110000000000100 m
b11 -
b11 f
b0 .
b0 e
b0 >
b0 T
b0 _
b0 p
b100 3
b100 d
b10011 6
b10011 V
b10100 L
b10100 [
b100110011 M
b10010001100000000001000010011 #
b10010001100000000001000010011 :
b10010001100000000001000010011 #"
b10100 4
b10000 $
b10000 +
b10000 {
b10000 5
b10000 ]
1!
#55000
0!
#60000
b1000000000000000 '
b1000000000000000 ?
b1000000000000000 b
b1000000000000000 z
0I
b10 a
b10 r
b1000000 )
b1000000 A
b1000000 u
b1000010 N
b1000010 h
b1000010 H
b1000010 S
b1000010 ^
b1000010 o
b10 Q
b1000000 F
b1000000 O
b10 E
b10 P
b0 8
b0 c
b1100 (
b1100 @
b1100 s
b1100 v
b1001000110000000000000000 &
b1001000110000000000000000 *
b1001000110000000000000000 w
b1001000110000000000000000 ,
b1001000110000000000000000 t
b10 ;
b10 n
b100100011 1
b100100011 j
b100100011 q
b1000000 2
b1000000 i
1%
17
b1 <
b1 Y
b1 l
00
1G
b1 .
b1 e
b1 >
b1 T
b1 _
b1 p
b1000000100100010 m
b0 =
b0 U
b100 -
b100 f
b10 3
b10 d
b100011 6
b100011 V
b11000 L
b11000 [
b10110 M
b10000001001000100100011 #
b10000001001000100100011 :
b10000001001000100100011 #"
b11000 4
b10100 $
b10100 +
b10100 {
b10100 5
b10100 ]
1!
#65000
0!
#70000
0`
b100100011 N
b100100011 h
b11111111111111111111111110000000 1
b11111111111111111111111110000000 j
b11111111111111111111111110000000 q
b0 (
b0 @
b0 s
b0 v
b0 &
b0 *
b0 w
b0 ,
b0 t
b1 /
b1 Z
10
0%
07
1G
b0 <
b0 Y
b0 l
b100100011 8
b100100011 c
b100000110100101 m
b10 -
b10 f
b101 >
b101 T
b101 _
b101 p
b101 3
b101 d
b11 6
b11 V
b1001000111000000000000000 '
b1001000111000000000000000 ?
b1001000111000000000000000 b
b1001000111000000000000000 z
b11100 L
b11100 [
b11010 M
b1000001101001010000011 #
b1000001101001010000011 :
b1000001101001010000011 #"
b11100 4
b11000 $
b11000 +
b11000 {
b11000 5
b11000 ]
1!
#75000
0!
#80000
b0 '
b0 ?
b0 b
b0 z
b1000 )
b1000 A
b1000 u
b1010 H
b1010 S
b1010 ^
b1010 o
b1010 Q
b0 F
b0 O
1K
1`
b1010 N
b1010 h
b1010 E
b1010 P
b1010 ;
b1010 n
b0 1
b0 j
b0 q
b0 2
b0 i
b0 8
b0 c
b100 (
b100 @
b100 s
b100 v
b0 &
b0 *
b0 w
b0 ,
b0 t
b0 /
b0 Z
10
1G
b10100000000000110 m
b1010 -
b1010 f
b0 .
b0 e
b0 >
b0 T
b0 _
b0 p
b110 3
b110 d
b10011 6
b10011 V
b100000 L
b100000 [
b100110 M
b101000000000001100010011 #
b101000000000001100010011 :
b101000000000001100010011 #"
b100000 4
b11100 $
b11100 +
b11100 {
b11100 5
b11100 ]
1!
#85000
0!
#90000
b1 (
b1 @
b1 s
b1 v
b0 a
b0 r
b10100 )
b10100 A
b10100 u
b10100 N
b10100 h
b10100 H
b10100 S
b10100 ^
b10100 o
b10100 Q
b10100 E
b10100 P
b10100 ;
b10100 n
b101000000000000111 m
b10100 -
b10100 f
b111 3
b111 d
b100100 L
b100100 [
b110100 M
b1010000000000001110010011 #
b1010000000000001110010011 :
b1010000000000001110010011 #"
b100100 4
b100000 $
b100000 +
b100000 {
b100000 5
b100000 ]
1!
#95000
0!
#100000
b10 a
b10 r
b11100 )
b11100 A
b11100 u
b11110 N
b11110 h
b11110 H
b11110 S
b11110 ^
b11110 o
b101000000000000000000 &
b101000000000000000000 *
b101000000000000000000 w
b101000000000000000000 ,
b101000000000000000000 t
b100 (
b100 @
b100 s
b100 v
b1010 F
b1010 O
0K
b111 ;
b111 n
b10100 1
b10100 j
b10100 q
b1010 2
b1010 i
10
0G
b110 .
b110 e
b1110011000001000 m
b111 -
b111 f
b1000 3
b1000 d
b110011 6
b110011 V
b101000 L
b101000 [
b101011 M
b11100110000010000110011 #
b11100110000010000110011 :
b11100110000010000110011 #"
b101000 4
b100100 $
b100100 +
b100100 {
b100100 5
b100100 ]
1!
#105000
0!
#110000
b0 a
b0 r
b1000100 )
b1000100 A
b1000100 u
b1000100 N
b1000100 h
b1000100 H
b1000100 S
b1000100 ^
b1000100 o
b100 Q
b1000000 F
b1000000 O
b100 E
b100 P
b1111 (
b1111 @
b1111 s
b1111 v
b11110 &
b11110 *
b11110 w
b11110 ,
b11110 t
b100 ;
b100 n
b11110 1
b11110 j
b11110 q
b1000000 2
b1000000 i
1%
17
b1 <
b1 Y
b1 l
1G
00
b10 >
b10 T
b10 _
b10 p
b10000000101000100 m
b1000 -
b1000 f
b1 .
b1 e
b100 3
b100 d
b100011 6
b100011 V
b101100 L
b101100 [
b101100 M
b100000001010001000100011 #
b100000001010001000100011 :
b100000001010001000100011 #"
b101100 4
b101000 $
b101000 +
b101000 {
b101000 5
b101000 ]
1!
#115000
0!
